<?xml version="1.0" encoding="UTF-8"?>
<files>
  <file name="1_1_1.afpk" source="derivative">
    <format>Columbia Peaks</format>
    <original>1_1_1.wav</original>
    <mtime>1470076919</mtime>
    <size>4568</size>
    <md5>c07c4fbafb09e1bd032e934b800f5f93</md5>
    <crc32>fef07647</crc32>
    <sha1>3b8add453670a80906dccdf1fcf8c2bb0d6ff536</sha1>
  </file>
  <file name="1_1_1.flac" source="derivative">
    <format>Flac</format>
    <original>1_1_1.wav</original>
    <mtime>1470076905</mtime>
    <size>563106</size>
    <md5>616ad3ae6cb85a3b7eb11e1d658e2928</md5>
    <crc32>9076d92d</crc32>
    <sha1>3da0d9edd314b09ab5651b08b663242b7dcd9f93</sha1>
    <length>28.5</length>
    <height>0</height>
    <width>0</width>
  </file>
  <file name="1_1_1.png" source="derivative">
    <format>PNG</format>
    <original>1_1_1.wav</original>
    <mtime>1470076909</mtime>
    <size>10733</size>
    <md5>3c1204bad524f3fdd8070330873b70fb</md5>
    <crc32>e5b61740</crc32>
    <sha1>d95c12d5f66ba2223a5ca6e3d0e52739d16017a2</sha1>
  </file>
  <file name="1_1_1.wav" source="original">
    <mtime>1470076872</mtime>
    <size>2513744</size>
    <md5>fdf8574e9f45228ae19439984dbb2a85</md5>
    <crc32>3ce12b3e</crc32>
    <sha1>10718bccca16393968bd5b9831bb6362eab4f234</sha1>
    <format>WAVE</format>
    <length>28.5</length>
    <track>01</track>
    <height>0</height>
    <width>0</width>
  </file>
  <file name="1_1_1_spectrogram.png" source="derivative">
    <format>Spectrogram</format>
    <original>1_1_1.wav</original>
    <mtime>1470076913</mtime>
    <size>130496</size>
    <md5>768bf7933e4b39785ad869ad2efe0acf</md5>
    <crc32>d31706cb</crc32>
    <sha1>0b73c75a974b3a5b0acd0a81f9c4b6bf9e6dede1</sha1>
  </file>
  <file name="1_1_2.afpk" source="derivative">
    <format>Columbia Peaks</format>
    <original>1_1_2.wav</original>
    <mtime>1470076930</mtime>
    <size>3696</size>
    <md5>614734403d526fa15469f387c6a9a733</md5>
    <crc32>6820c6ff</crc32>
    <sha1>f3cc86d7e85a066004d487ad28c5c9c74d872a45</sha1>
  </file>
  <file name="1_1_2.flac" source="derivative">
    <format>Flac</format>
    <original>1_1_2.wav</original>
    <mtime>1470076906</mtime>
    <size>1064632</size>
    <md5>ec54075e4626bedb6fafad15d066fa65</md5>
    <crc32>67983270</crc32>
    <sha1>113bc3d0859803855360e3868c1f329bca03fda6</sha1>
    <length>28.5</length>
    <height>0</height>
    <width>0</width>
  </file>
  <file name="1_1_2.png" source="derivative">
    <format>PNG</format>
    <original>1_1_2.wav</original>
    <mtime>1470076912</mtime>
    <size>10827</size>
    <md5>9829ebde2b830d8960d796699783d02e</md5>
    <crc32>af48f562</crc32>
    <sha1>7ae94ee51f2c9cdd22996bcdd2919d6291fab028</sha1>
  </file>
  <file name="1_1_2.wav" source="original">
    <mtime>1470076882</mtime>
    <size>2513744</size>
    <md5>29dd8f577131d79573c71a9a57c90f92</md5>
    <crc32>d1ce2681</crc32>
    <sha1>6918a21d1ffbf56c346de94a90e91d0bef83cb81</sha1>
    <format>WAVE</format>
    <length>28.5</length>
    <track>02</track>
    <height>0</height>
    <width>0</width>
  </file>
  <file name="1_1_2_spectrogram.png" source="derivative">
    <format>Spectrogram</format>
    <original>1_1_2.wav</original>
    <mtime>1470076914</mtime>
    <size>141368</size>
    <md5>377130001a1cba97f3fa111887a2ffd0</md5>
    <crc32>d0cd4b15</crc32>
    <sha1>74976c0dded822ebe243b4eab3ae2173ea9d4bb6</sha1>
  </file>
  <file name="__ia_thumb.jpg" source="original">
    <mtime>1613517307</mtime>
    <size>3707</size>
    <md5>4522b9ee77451b43d1fe9d6c074e8c17</md5>
    <crc32>a7927cd9</crc32>
    <sha1>b3dcb34128e1ce14e749ac8357505bfd05184cc1</sha1>
    <format>Item Tile</format>
    <rotation>0</rotation>
  </file>
  <file name="melody_dataset_archive.torrent" source="metadata">
    <btih>9308885a8e33d6d407108accaedb7fccd3397cfc</btih>
    <mtime>1613517308</mtime>
    <size>3729</size>
    <md5>7d483d34dedffc4e2ee66b6b7335cc34</md5>
    <crc32>b0dd0f10</crc32>
    <sha1>0923e02a89e468927191de9b539027109f024b4c</sha1>
    <format>Archive BitTorrent</format>
  </file>
  <file name="melody_dataset_files.xml" source="metadata">
    <format>Metadata</format>
    <md5>535628bbe131daffe7ad8c0cf971fbf6</md5>
    <summation>md5</summation>
  </file>
  <file name="melody_dataset_meta.sqlite" source="original">
    <mtime>1470076887</mtime>
    <size>14336</size>
    <md5>a386186a09bcb520c9304067f235b1f1</md5>
    <crc32>bb26f8e9</crc32>
    <sha1>1bd84fd8a1e5a3c3453b1f58a9f4d09a98f1c034</sha1>
    <format>Metadata</format>
  </file>
  <file name="melody_dataset_meta.xml" source="metadata">
    <mtime>1613517307</mtime>
    <size>1486</size>
    <format>Metadata</format>
    <md5>9dd4ea69c045ab7e00ad055608a45ba1</md5>
    <crc32>d70f2145</crc32>
    <sha1>5d419ba437de64fffe893fdd4dd93fe3dd8cb924</sha1>
  </file>
  <file name="melody_dataset_rules.conf" source="original">
    <mtime>1470077052</mtime>
    <size>9</size>
    <md5>c6252ae91bcb6e4c9db553057479e7d3</md5>
    <crc32>4ae60840</crc32>
    <sha1>fc079ae018899da82fd9dd027c241e886b050c8a</sha1>
    <format>Derivation Rules</format>
  </file>
</files>
